[
  {
    "PartyName": "Bahujan-Samaj-Party-",
    "Name": "Nil",
    "Address": "Nil",
    "PAN Given": "N",
    "Amount": 0,
    "Contribution Mode": "Nil",
    "Financial Year": "2014-15"
  },
  {
    "PartyName": "Bahujan-Samaj-Party-",
    "Name": "Nil",
    "Address": "Nil",
    "PAN Given": "N",
    "Amount": 0,
    "Contribution Mode": "Nil",
    "Financial Year": "2013-14"
  },
  {
    "PartyName": "Bahujan-Samaj-Party-",
    "Name": "Nil",
    "Address": "Nil",
    "PAN Given": "N",
    "Amount": 0,
    "Contribution Mode": "Nil",
    "Financial Year": "2012-13"
  },
  {
    "PartyName": "Bahujan-Samaj-Party-",
    "Name": "Nil",
    "Address": "Nil",
    "PAN Given": "N",
    "Amount": 0,
    "Contribution Mode": "Nil",
    "Financial Year": "2011-12"
  },
  {
    "PartyName": "Bahujan-Samaj-Party-",
    "Name": "Nil",
    "Address": "Nil",
    "PAN Given": "N",
    "Amount": 0,
    "Contribution Mode": "Nil",
    "Financial Year": "2010-11"
  },
  {
    "PartyName": "Bahujan-Samaj-Party-",
    "Name": "Nil",
    "Address": "Nil",
    "PAN Given": "N",
    "Amount": 0,
    "Contribution Mode": "Nil",
    "Financial Year": "2009-10"
  },
  {
    "PartyName": "Bahujan-Samaj-Party-",
    "Name": "Nil",
    "Address": "Nil",
    "PAN Given": "N",
    "Amount": 0,
    "Contribution Mode": "Nil",
    "Financial Year": "2008-09"
  },
  {
    "PartyName": "Bahujan-Samaj-Party-",
    "Name": "Nil",
    "Address": "Nil",
    "PAN Given": "N",
    "Amount": 0,
    "Contribution Mode": "Nil",
    "Financial Year": "2007-08"
  },
  {
    "PartyName": "Bahujan-Samaj-Party-",
    "Name": "Nil",
    "Address": "Nil",
    "PAN Given": "N",
    "Amount": 0,
    "Contribution Mode": "Nil",
    "Financial Year": "2005-06"
  },
  {
    "PartyName": "Bahujan-Samaj-Party-",
    "Name": "Nil",
    "Address": "Nil",
    "PAN Given": "N",
    "Amount": 0,
    "Contribution Mode": "Nil",
    "Financial Year": "2003-04"
  },
  {
    "PartyName": "Bahujan-Samaj-Party-",
    "Name": "Nil",
    "Address": "Nil",
    "PAN Given": "N",
    "Amount": 0,
    "Contribution Mode": "Nil",
    "Financial Year": "2002-03"
  },
  {
    "PartyName": "Bahujan-Samaj-Party-",
    "Name": "Nil",
    "Address": "Nil",
    "PAN Given": "N",
    "Amount": 0,
    "Contribution Mode": "Nil",
    "Financial Year": "2001-02"
  },
  {
    "PartyName": "Bahujan-Samaj-Party-",
    "Name": "",
    "Address": "--",
    "PAN Given": "N",
    "Amount": 0,
    "Contribution Mode": "",
    "Financial Year": "2015-16"
  }
]